UWGeodynamics/__init__.py
UWGeodynamics/_boundary_conditions.py
UWGeodynamics/_density.py
UWGeodynamics/_freesurface.py
UWGeodynamics/_frictional_boundary.py
UWGeodynamics/_material.py
UWGeodynamics/_melt.py
UWGeodynamics/_mesh_advector.py
UWGeodynamics/_model.py
UWGeodynamics/_rcParams.py
UWGeodynamics/_remeshing.py
UWGeodynamics/_rheology.py
UWGeodynamics/_utils.py
UWGeodynamics/_validate.py
UWGeodynamics/_visugrid.py
UWGeodynamics/shapes.py
UWGeodynamics/surfaceProcesses.py
UWGeodynamics/version.py
UWGeodynamics/LecodeIsostasy/LecodeIsostasy.py
UWGeodynamics/LecodeIsostasy/__init__.py
UWGeodynamics/_net/__init__.py
UWGeodynamics/lithopress/__init__.py
UWGeodynamics/lithopress/lithopress.py
UWGeodynamics/postprocessing/__init__.py
UWGeodynamics/postprocessing/_logFile.py
UWGeodynamics/postprocessing/_tracers.py
UWGeodynamics/ressources/Liquidus.json
UWGeodynamics/ressources/Materials.json
UWGeodynamics/ressources/PlasticRheologies.json
UWGeodynamics/ressources/Solidus.json
UWGeodynamics/ressources/ViscousRheologies.json
UWGeodynamics/utilities/UWtoAscii.py
UWGeodynamics/utilities/__init__.py
UWGeodynamics/uwgeo-data/uwgeodynamicsrc
UWGeodynamics-2.12.5.dist-info/LICENSE.md
UWGeodynamics-2.12.5.dist-info/METADATA
UWGeodynamics-2.12.5.dist-info/WHEEL
UWGeodynamics-2.12.5.dist-info/entry_points.txt
UWGeodynamics-2.12.5.dist-info/top_level.txt
UWGeodynamics-2.12.5.dist-info/RECORD
