Metadata-Version: 2.1
Name: UWGeodynamics
Version: 2.12.5
Summary: Underworld Geodynamics wrapper
Home-page: https://github.com/rbeucher/UWGeodynamics.git
Author: Romain Beucher
Author-email: romain.beucher@anu.edu.au
License: UNKNOWN
Keywords: geodynamics Underworld geophysics geology
Platform: UNKNOWN
Classifier: Development Status :: 5 - Production/Stable
Classifier: Intended Audience :: Developers
Classifier: Topic :: Software Development :: Build Tools
Classifier: License :: OSI Approved :: GNU General Public License v3 or later (GPLv3+)
Classifier: Programming Language :: Python :: 3.3
Classifier: Programming Language :: Python :: 3.4
Classifier: Programming Language :: Python :: 3.5
Classifier: Programming Language :: Python :: 3.6
Classifier: Programming Language :: Python :: 3.7
Classifier: Programming Language :: Python :: 3.8
Classifier: Programming Language :: Python :: 3.9
Requires-Dist: numpy
Requires-Dist: pint
Requires-Dist: scipy
